sslib/__init__.py
sslib/main.py
sslib/base/__init__.py
sslib/base/db_conn.py
sslib/base/dict.py
sslib/base/entity.py
sslib/decorator/__init__.py
sslib/decorator/singleton.py
sslib/decorator/time_checker.py
sslib/helper/__init__.py
sslib/helper/config.py
sslib/helper/mysql.py
sslib/helper/slack.py
sslib/klass/__init__.py
sslib/klass/bit_flag.py
sslib/klass/crypto.py
sslib/service/__init__.py
sslib/service/base_service.py
sslib/service/httpx_service.py
sslib/util/__init__.py
sslib/util/datetime_util.py
sslib/util/dict_util.py
sslib/util/json_util.py
sslib/util/number_util.py
sslib/util/string_util.py
ss_pylib-0.27.3.dist-info/METADATA
ss_pylib-0.27.3.dist-info/WHEEL
ss_pylib-0.27.3.dist-info/entry_points.txt
ss_pylib-0.27.3.dist-info/top_level.txt
ss_pylib-0.27.3.dist-info/RECORD
