Metadata-Version: 2.4
Name: ss-pylib
Version: 0.27.3
Summary: SWEET-SOOP Python Library
Author: sweetsoop
Author-email: sweetsoop@gmail.com
License: MIT
Requires-Python: >=3.12
Requires-Dist: httpx
Requires-Dist: PyMySQL
Requires-Dist: stringcase
Requires-Dist: cryptography
Requires-Dist: python-dateutil
Requires-Dist: dataclasses-json
Requires-Dist: typing-extensions
Dynamic: author
Dynamic: author-email
Dynamic: description
Dynamic: description-content-type
Dynamic: license
Dynamic: requires-dist
Dynamic: requires-python
Dynamic: summary
